jwst_rogue_path_tool/__init__.py
jwst_rogue_path_tool/constants.py
jwst_rogue_path_tool/detect_claws.py
jwst_rogue_path_tool/fixed_angle.py
jwst_rogue_path_tool/plotting.py
jwst_rogue_path_tool/program_data_parser.py
jwst_rogue_path_tool/utils.py
jwst_rogue_path_tool/data/APT_test_4RPtool.records.json
jwst_rogue_path_tool/data/filter_data.txt
jwst_rogue_path_tool/data/rogue_path_nrca.fits
jwst_rogue_path_tool/data/rogue_path_nrcb.fits
jwst_rogue_path_tool/data/two_mass_kmag_lt_5.csv
jwst_rogue_path_tool/notebooks/jwst_rogue_path_tool_demo.ipynb
jwst_rogue_path_tool/notebooks/nircam_observer_example.ipynb
jwst_rogue_path_tool/original_src/apt_sql.py
jwst_rogue_path_tool/original_src/claws_tool.py
jwst_rogue_path_tool/scripts/output_results.py
jwst_rogue_path_tool/tests/test_apt_json_parser.py
jwst_rogue_path_tool/tests/test_utils.py
jwst_rogue_path_tool-1.1.0.dist-info/METADATA
jwst_rogue_path_tool-1.1.0.dist-info/WHEEL
jwst_rogue_path_tool-1.1.0.dist-info/entry_points.txt
jwst_rogue_path_tool-1.1.0.dist-info/top_level.txt
jwst_rogue_path_tool-1.1.0.dist-info/RECORD
